{
  "movies": [
    {
      "id": 1,
      "dvdNumber": 12,
      "genre": "Drama",
      "year": 12312,
      "time": 12312,
      "movieTitle": "edites",
      "cast": "123",
      "coverUrl": "https://encrypted-tbn0.gstatic.com/images?q=tbn:ANd9GcSgTDOzadSH7HZlU96Ogy2XzMynwk4o4Epcvw12FmpBYRT0B_aLrA",
      "trailerUrl": "https://www.youtube.com/embed/MYm5iaOy6Ik"
    },
    {
      "id": 2,
      "dvdNumber": 12,
      "genre": "Comedy",
      "year": 1595,
      "time": 616,
      "movieTitle": "batman2",
      "cast": "afkaso",
      "coverUrl": "aslfklafa ",
      "trailerUrl": "https://www.youtube.com/embed/keJikcDWL88&index=14&list=PLGLnGPAvPbuBJXz23cOWWwQn4VK9Snwwr"
    },
    {
      "id": 3,
      "dvdNumber": 22,
      "genre": "Comedy",
      "year": 1996,
      "time": 150,
      "movieTitle": "Tomb Raider",
      "cast": "angelina jolie, tom cruze, bred pitt",
      "coverUrl": "https://m.media-amazon.com/images/M/MV5BNWYyNDIxNDYtYTkxMi00ZGI3LWJmZmEtOGU3YTQ2MjVmYTAyXkEyXkFqcGdeQXVyNTk5ODgwNTE@._V1_UX182_CR0,0,182,268_AL_.jpg",
      "trailerUrl": "https://www.youtube.com/embed/xBIQxDA6cPo"
    },
    {
      "id": 5,
      "dvdNumber": 22,
      "genre": "Musical",
      "year": 2015,
      "time": 214,
      "movieTitle": "Anacondas: The Hunt for the Blood Orchid 2",
      "cast": "asfasfa",
      "coverUrl": "https://m.media-amazon.com/images/M/MV5BNGU4MThiYjItMDliMC00YWM4LTljZTEtNTg0YzdiMmE2MjM4XkEyXkFqcGdeQXVyMTQxNzMzNDI@._V1_SX663_CR0,0,663,999_AL_.jpg",
      "trailerUrl": "https://www.youtube.com/embed/yKPSBbufbME"
    }
  ]
}